LICENSE
MANIFEST.in
README.md
quicktest.py
settings_test.py
setup.py
django_twitter_relations_history.egg-info/PKG-INFO
django_twitter_relations_history.egg-info/SOURCES.txt
django_twitter_relations_history.egg-info/dependency_links.txt
django_twitter_relations_history.egg-info/not-zip-safe
django_twitter_relations_history.egg-info/requires.txt
django_twitter_relations_history.egg-info/top_level.txt
twitter_relations_history/__init__.py
twitter_relations_history/__init__.pyc
twitter_relations_history/admin.py
twitter_relations_history/factories.py
twitter_relations_history/models.py
twitter_relations_history/models.pyc
twitter_relations_history/signals.py
twitter_relations_history/signals.pyc
twitter_relations_history/tasks.py
twitter_relations_history/tests.py
twitter_relations_history/tests.pyc
twitter_relations_history/migrations/0001_initial.py
twitter_relations_history/migrations/0001_initial.pyc
twitter_relations_history/migrations/0002_auto__add_relationshistorydelta__add_unique_relationshistorydelta_hist.pyc
twitter_relations_history/migrations/__init__.pyc