Metadata-Version: 1.1
Name: django-twitter-relations-history
Version: 0.3.8
Summary: Django implementation for storing twitter user relations history
Home-page: https://github.com/ramusus/django-twitter-relations-history
Author: ramusus
Author-email: ramusus@gmail.com
License: BSD
Download-URL: http://pypi.python.org/pypi/django-twitter-relations-history
Platform: UNKNOWN
Classifier: Development Status :: 4 - Beta
Classifier: Environment :: Web Environment
Classifier: Intended Audience :: Developers
Classifier: License :: OSI Approved :: BSD License
Classifier: Operating System :: OS Independent
Classifier: Programming Language :: Python
Classifier: Topic :: Software Development :: Libraries :: Python Modules
